{
  "success": true,
  "data": {
    "legs": [
      {
        "id": "181913649",
        "name": "Five Elephant Legs",
        "url": "legs/elephant.png",
        "width": 1200,
        "height": 1200,
        "box_count": 2
      },
      {
        "id": "112126428",
        "name": "horse",
        "url": "legs/horse.png",
        "width": 1200,
        "height": 800,
        "box_count": 3
      },
      {
        "id": "87743020",
        "name": "mouth feet",
        "url": "legs/mouth feet.png",
        "width": 600,
        "height": 908,
        "box_count": 2
      },
      {
        "id": "129242436",
        "name": "Six Kitty Legs",
        "url": "legs/six kitty legs.png",
        "width": 482,
        "height": 361,
        "box_count": 2
      },
      {
        "id": "129242436",
        "name": "Ursula",
        "url": "legs/tentacles.png",
        "width": 482,
        "height": 361,
        "box_count": 2
      },
      {
        "id": "131087935",
        "name": "Fat Walrus",
        "url": "legs/walrus.png",
        "width": 761,
        "height": 1024,
        "box_count": 5
      }
    ]
  }
}
